lightstreamer/client/__init__.py
lightstreamer/client/com_lightstreamer_net.py
lightstreamer/client/ls_python_client_api.py
lightstreamer/client/ls_python_client_haxe.py
lightstreamer/client/ls_python_client_wrapper.py
lightstreamer_client_lib-2.2.2.dist-info/licenses/LICENSE
lightstreamer_client_lib-2.2.2.dist-info/METADATA
lightstreamer_client_lib-2.2.2.dist-info/WHEEL
lightstreamer_client_lib-2.2.2.dist-info/top_level.txt
lightstreamer_client_lib-2.2.2.dist-info/RECORD
