Metadata-Version: 2.4
Name: lightstreamer-client-lib
Version: 2.2.2
Summary: Lightstreamer Client SDK
Author-email: Lightstreamer Srl <support@lightstreamer.com>
License: Apache-2.0
Project-URL: Homepage, https://github.com/Lightstreamer/Lightstreamer-lib-client-haxe
Keywords: lightstreamer,push,realtime,real-time
Classifier: License :: OSI Approved :: Apache Software License
Classifier: Programming Language :: Python :: 3
Classifier: Topic :: Communications
Classifier: Topic :: Software Development :: Libraries
Requires-Python: >=3.7
License-File: LICENSE
Requires-Dist: aiohttp>=3.8.6
Requires-Dist: jsonpatch>=1.33
Dynamic: license-file
